MANIFEST.in
README.txt
setup.cfg
setup.py
docs/HISTORY.txt
docs/INSTALL.txt
docs/LICENSE.GPL
docs/LICENSE.txt
jalon/__init__.py
jalon.bdd.egg-info/PKG-INFO
jalon.bdd.egg-info/SOURCES.txt
jalon.bdd.egg-info/dependency_links.txt
jalon.bdd.egg-info/entry_points.txt
jalon.bdd.egg-info/namespace_packages.txt
jalon.bdd.egg-info/not-zip-safe
jalon.bdd.egg-info/paster_plugins.txt
jalon.bdd.egg-info/requires.txt
jalon.bdd.egg-info/top_level.txt
jalon/bdd/__init__.py
jalon/bdd/configure.zcml
jalon/bdd/skins.zcml
jalon/bdd/tests.py
jalon/bdd/browser/__init__.py
jalon/bdd/browser/configure.zcml
jalon/bdd/browser/interfaces.py
jalon/bdd/browser/javascripts/gestionBDD.js
jalon/bdd/browser/scripts/__init__.py
jalon/bdd/browser/scripts/connecteurbdd.py
jalon/bdd/browser/templates/jalon_connecteur_bdd.pt
jalon/bdd/content/__init__.py
jalon/bdd/content/configure.zcml
jalon/bdd/content/interfaces.py
jalon/bdd/content/jalon_mysql.py
jalon/bdd/content/jalonbdd.py
jalon/bdd/content/jalonsqlite.py
jalon/bdd/content/tables/__init__.py
jalon/bdd/content/tables/actualitescours.py
jalon/bdd/content/tables/connexionind.py
jalon/bdd/content/tables/consultationcours.py
jalon/bdd/content/tables/elementpedagogi.py
jalon/bdd/content/tables/elpregroupeelp.py
jalon/bdd/content/tables/gpeobj.py
jalon/bdd/content/tables/groupe.py
jalon/bdd/content/tables/indaffectegpe.py
jalon/bdd/content/tables/indcontratelp.py
jalon/bdd/content/tables/individu.py
jalon/bdd/content/tables/insadmetp.py
jalon/bdd/content/tables/peers_evaluation.py
jalon/bdd/content/tables/vdifractionnervet.py
jalon/bdd/content/tables/versionetape.py
jalon/bdd/profiles/default/componentregistry.xml
jalon/bdd/profiles/default/controlpanel.xml
jalon/bdd/profiles/default/jsregistry.xml
jalon/bdd/profiles/default/metadata.xml
jalon/bdd/profiles/default/skins.xml
jalon/bdd/profiles/default/toolset.xml
jalon/bdd/skins/jalon_bdd/activerUtilisateur_script.py
jalon/bdd/skins/jalon_bdd/attachELP.py
jalon/bdd/skins/jalon_bdd/bloquerUtilisateur_script.py
jalon/bdd/skins/jalon_bdd/compositionELP_script.py
jalon/bdd/skins/jalon_bdd/creerELP_script.py
jalon/bdd/skins/jalon_bdd/creerUtilisateur_script.py
jalon/bdd/skins/jalon_bdd/demanderSuppressionUtilisateur_script.py
jalon/bdd/skins/jalon_bdd/desinscriptEnsResp.py
jalon/bdd/skins/jalon_bdd/gestion_bdd.pt
