Metadata-Version: 1.1
Name: jalon.bdd
Version: 3.0
Summary: Gestion de l'offre de formation de Jalon
Home-page: http://svn.plone.org/svn/collective/
Author: Bordonado Christophe (Université Nice Sophia Antipolis Service TICE), Marc Martinot
Author-email: tice@unice.fr
License: GPL
Platform: UNKNOWN
Classifier: Framework :: Plone
Classifier: Programming Language :: Python
